robocorp/workitems/__init__.py
robocorp/workitems/_adapters/__init__.py
robocorp/workitems/_adapters/_base.py
robocorp/workitems/_adapters/_file.py
robocorp/workitems/_adapters/_robocorp.py
robocorp/workitems/_context.py
robocorp/workitems/_exceptions.py
robocorp/workitems/_requests.py
robocorp/workitems/_types.py
robocorp/workitems/_utils.py
robocorp/workitems/_workitem.py
robocorp/workitems/py.typed
robocorp_workitems-1.4.4.dist-info/METADATA
robocorp_workitems-1.4.4.dist-info/WHEEL
robocorp_workitems-1.4.4.dist-info/RECORD
