Metadata-Version: 2.1
Name: robocorp-workitems
Version: 1.4.4
Summary: Robocorp Work Items library
Home-page: https://github.com/robocorp/robocorp/
License: Apache-2.0
Author: Fabio Z.
Author-email: fabio@robocorp.com
Requires-Python: >=3.9,<4.0
Classifier: License :: OSI Approved :: Apache Software License
Classifier: Programming Language :: Python :: 3
Classifier: Programming Language :: Python :: 3.9
Classifier: Programming Language :: Python :: 3.10
Classifier: Programming Language :: Python :: 3.11
Classifier: Programming Language :: Python :: 3.12
Requires-Dist: dataclasses-json (>=0.6.1,<0.7.0)
Requires-Dist: python-dateutil (>=2.8.2,<3.0.0)
Requires-Dist: requests (>=2.28.2,<3.0.0)
Requires-Dist: robocorp-tasks (>=1,<4)
Requires-Dist: tenacity (>=8.0.1,<9.0.0)
Project-URL: Repository, https://github.com/robocorp/robocorp/
